chungus_explainer/__init__.py
chungus_explainer/chungus.py
chungus_explainer/data_validation.py
chungus_explainer/prompt_engineer.py
chungus_explainer-0.1.8.dist-info/LICENSE
chungus_explainer-0.1.8.dist-info/METADATA
chungus_explainer-0.1.8.dist-info/WHEEL
chungus_explainer-0.1.8.dist-info/top_level.txt
chungus_explainer-0.1.8.dist-info/RECORD
