Metadata-Version: 2.1
Name: chungus-explainer
Version: 0.1.8
Summary: A library that incorportates ChatGPT to help users read Shap values.
Author: Yap Hong Jun
Author-email: yaphongjun@gmail.com
Classifier: Programming Language :: Python :: 3
Classifier: License :: OSI Approved :: MIT License
Classifier: Operating System :: OS Independent
Requires-Python: >=3.6
License-File: LICENSE
